django_database_prefix/__init__.py
django_database_prefix/models.py
django_database_prefix-0.1.0.dist-info/LICENSE
django_database_prefix-0.1.0.dist-info/METADATA
django_database_prefix-0.1.0.dist-info/WHEEL
django_database_prefix-0.1.0.dist-info/top_level.txt
django_database_prefix-0.1.0.dist-info/RECORD
