Metadata-Version: 2.1
Name: django-database-prefix
Version: 0.1.0
Summary: UNKNOWN
Home-page: https://github.com/rez0n/django-database-prefix
Author: Denis Verbin <den.verbin@gmail.com
License: Apache licence, see LICENCE
Keywords: django
Platform: UNKNOWN
Classifier: Framework :: Django
Classifier: Topic :: Database
Requires: Django
License-File: LICENSE
